setup.py
first_message_serverver_from_lev.egg-info/PKG-INFO
first_message_serverver_from_lev.egg-info/SOURCES.txt
first_message_serverver_from_lev.egg-info/dependency_links.txt
first_message_serverver_from_lev.egg-info/requires.txt
first_message_serverver_from_lev.egg-info/top_level.txt
server/__init__.py
server/db_class_server.py
server/descrptrs.py
server/launcher_ver_2.0.py
server/metaclass.py
server/server_class.py
server/common/__init__.py
server/common/external_func.py
server/common/vars.py