Metadata-Version: 1.0
Name: first-message-serverver-from-lev
Version: 0.0.1
Summary: first_message_serverver_from_lev
Home-page: UNKNOWN
Author: Lev Khotylev
Author-email: email_email@yandex.ru
License: UNKNOWN
Platform: UNKNOWN
